absbox/__init__.py
absbox/client.py
absbox/deal.py
absbox/exception.py
absbox/library.py
absbox/report.py
absbox/rootFinder.py
absbox/validation.py
absbox/examples/__init__.py
absbox/examples/baseCase.py
absbox/examples/mixAssetType.py
absbox/examples/triggerCase.py
absbox/local/__init__.py
absbox/local/analytics.py
absbox/local/base.py
absbox/local/cf.py
absbox/local/chart.py
absbox/local/china.py
absbox/local/cmp.py
absbox/local/component.py
absbox/local/generic.py
absbox/local/interface.py
absbox/local/plot.py
absbox/local/util.py
absbox/report_parser/__init__.py
absbox/report_parser/china.py
absbox-0.52.1.dist-info/licenses/LICENSE
absbox-0.52.1.dist-info/METADATA
absbox-0.52.1.dist-info/WHEEL
absbox-0.52.1.dist-info/top_level.txt
absbox-0.52.1.dist-info/RECORD
