Metadata-Version: 2.4
Name: absbox
Version: 0.52.1
Summary: an analytical library for cashflow modeling on ABS/MBS products
Home-page: https://github.com/yellowbean/PyABS
Download-URL: https://github.com/yellowbean/AbsBox/archive/refs/heads/main.zip
Author: xiaoyu, zhang
Author-email: always.zhang@gmail.com
License:                                  Apache License
Project-URL: homepage, https://absbox.org
Project-URL: documentation, https://absbox-doc.readthedocs.io/en/latest/
Project-URL: repository, https://github.com/yellowbean/AbsBox/
Project-URL: changelog, https://github.com/yellowbean/AbsBox/blob/main/CHANGELOG.rst
Keywords: cashflow,abs,mbs,cashflow model,rmbs,clo,cashflow engine,structuring,srt
Classifier: Development Status :: 4 - Beta
Classifier: Environment :: Console
Classifier: Intended Audience :: Developers
Classifier: Intended Audience :: Financial and Insurance Industry
Classifier: Topic :: Software Development :: Build Tools
Classifier: Topic :: Software Development :: Libraries
Classifier: License :: OSI Approved :: MIT License
Requires-Python: >=3.10
License-File: LICENSE
Requires-Dist: pandas
Requires-Dist: numpy
Requires-Dist: requests
Requires-Dist: toolz
Requires-Dist: rich
Requires-Dist: lenses
Requires-Dist: graphviz
Requires-Dist: schema
Requires-Dist: htpy
Requires-Dist: dateparser
Requires-Dist: more-itertools
Requires-Dist: xlsxwriter
Requires-Dist: faker
Requires-Dist: numpy-financial
Provides-Extra: test
Requires-Dist: pytest; extra == "test"
Requires-Dist: jsondiff; extra == "test"
Requires-Dist: deepdiff; extra == "test"
Requires-Dist: ipykernel; extra == "test"
Requires-Dist: pytest-notebook; extra == "test"
Requires-Dist: marimo; extra == "test"
Dynamic: download-url
Dynamic: license-file
